mediacontroller/__init__.py
mediacontroller/main.py
mediagesture-0.1.0.dist-info/METADATA
mediagesture-0.1.0.dist-info/WHEEL
mediagesture-0.1.0.dist-info/entry_points.txt
mediagesture-0.1.0.dist-info/top_level.txt
mediagesture-0.1.0.dist-info/RECORD
